mape/__init__.py
mape/application.py
mape/base_elements.py
mape/config.py
mape/constants.py
mape/knowledge.py
mape/level.py
mape/loop.py
mape/mape.default.yml
mape/operators.py
mape/remote/__init__.py
mape/remote/de_serializer.py
mape/remote/influxdb/__init__.py
mape/remote/influxdb/rx_utils.py
mape/remote/redis/__init__.py
mape/remote/redis/collections_patch.py
mape/remote/redis/pubsub.py
mape/remote/redis/rx_utils.py
mape/remote/rest/__init__.py
mape/remote/rest/api.py
mape/remote/rest/rx_utils.py
mape/remote/rest/setup.py
mape/remote/rest/webserver.py
mape/typing.py
mape/utils.py
pymape-0.1.0a5.dist-info/LICENSE
pymape-0.1.0a5.dist-info/METADATA
pymape-0.1.0a5.dist-info/WHEEL
pymape-0.1.0a5.dist-info/RECORD
