Metadata-Version: 2.1
Name: pymape
Version: 0.1.0a5
Summary: Framework to develop Self-Adaptive system based on MAPE-K loop.
Home-page: https://elbowz.github.io/PyMAPE/
License: GPL-3.0-only
Keywords: mape,mapek,mape-k,self-adaptive,autonomus system
Author: Emanuele Palombo
Author-email: muttley.bd@gmail.com
Requires-Python: >=3.8,<4.0
Classifier: License :: OSI Approved :: Apache Software License
Classifier: License :: OSI Approved :: GNU General Public License v3 (GPLv3)
Classifier: Operating System :: OS Independent
Classifier: Programming Language :: Python :: 3
Classifier: Programming Language :: Python :: 3.8
Classifier: Programming Language :: Python :: 3.9
Classifier: Programming Language :: Python :: 3.10
Classifier: Programming Language :: Python :: 3.11
Classifier: Programming Language :: Python :: 3
Classifier: Topic :: Scientific/Engineering
Classifier: Topic :: Software Development :: Libraries :: Python Modules
Requires-Dist: PyYAML (>=6.0,<7.0)
Requires-Dist: Rx (>=3.2.0,<4.0.0)
Requires-Dist: aiohttp (>=3.8.1,<4.0.0)
Requires-Dist: fastapi (>=0.73,<0.74)
Requires-Dist: influxdb-client (>=1.26.0,<2.0.0)
Requires-Dist: redis-purse (>=0.25.0,<0.26.0)
Requires-Dist: uvicorn (>=0.17.4,<0.18.0)
Project-URL: Documentation, https://elbowz.github.io/PyMAPE/
Project-URL: Repository, https://github.com/elbowz/PyMAPE
